Metadata-Version: 2.1
Name: VideoAmodal
Version: 0.0.0
Summary: HiZXtman  sdafaf safafa sfsdf
Home-page: UNKNOWN
Author: sharmajiii
Author-email: sharmaji@ict.com
License: UNKNOWN
Platform: UNKNOWN
Classifier: Programming Language :: Python :: 3
Classifier: License :: OSI Approved :: MIT License
Classifier: Operating System :: OS Independent
License-File: LICENSE.txt
